deconomix/__init__.py
deconomix/methods.py
deconomix/utils.py
deconomix-1.0.1.dist-info/LICENSE
deconomix-1.0.1.dist-info/METADATA
deconomix-1.0.1.dist-info/WHEEL
deconomix-1.0.1.dist-info/top_level.txt
deconomix-1.0.1.dist-info/RECORD
