Metadata-Version: 2.1
Name: deconomix
Version: 1.0.1
Summary: Provides methods for cellular composition, hidden background and gene regulation estimation of omics bulk mixtures.
Author: Malte Mensching-Buhr, Thomas Sterr, Nicole Seifert, Dennis Voelkl, Jana Tauschke, Austin Rayford, Helena U. Zacharias, Sushma Nagaraja Grellscheid, Tim Beissbarth,  Franziska Goertler, Michael Altenbuchinger
Author-email: michael.altenbuchinger@bioinf.med.uni-goettingen.de
License-File: LICENSE
Requires-Dist: torch>=2.5.0
Requires-Dist: numpy>=1.23.0
Requires-Dist: scikit-learn
Requires-Dist: qpsolvers>=4.3.2
Requires-Dist: qpsolvers[quadprog]
Requires-Dist: qpsolvers[scs]
Requires-Dist: qpsolvers[clarabel]
Requires-Dist: matplotlib
Requires-Dist: pandas>=2.2.2
Requires-Dist: pyarrow
Requires-Dist: seaborn
Requires-Dist: scipy
Requires-Dist: tqdm>=4.66.4
Requires-Dist: ipywidgets
